Metadata-Version: 1.0
Name: tiddlywebplugins.cherrypy
Version: 0.1.1
Summary: An improved server for TiddlyWeb.
Home-page: http://pypi.python.org/pypi/tiddlywebplugins.cherrypy
Author: Chris Dent
Author-email: cdent@peermore.com
License: UNKNOWN
Platform: Posix; MacOS X; Windows
Classifier: Environment :: Web Environment
Classifier: License :: OSI Approved :: BSD License
Classifier: Operating System :: OS Independent
Classifier: Programming Language :: Python :: 2.7
Classifier: Programming Language :: Python :: 3.3
Classifier: Topic :: Internet :: WWW/HTTP :: WSGI
